firebolt/__init__.py
firebolt/__main__.py
firebolt/wsgi.py
firebolt-0.0.1.dist-info/DESCRIPTION.rst
firebolt-0.0.1.dist-info/METADATA
firebolt-0.0.1.dist-info/RECORD
firebolt-0.0.1.dist-info/WHEEL
firebolt-0.0.1.dist-info/metadata.json
firebolt-0.0.1.dist-info/top_level.txt
